chinese_dict/__init__.py
chinese_dict/__main__.py
chinese_dict/chinese_dict.py
chinese_dict/handict.py
chinese_dict/main.py
chinese_dict/classes/__init__.py
chinese_dict/classes/charresult.py
chinese_dict/classes/models.py
chinese_dict/errors/NotFound.py
chinese_dict/errors/__init__.py
chinese_dict/helpers/__init__.py
chinese_dict/helpers/cleaner.py
chinese_dict/helpers/converter.py
chinese_dict-0.2.0.data/data/data/hanlearn.db
chinese_dict-0.2.0.dist-info/METADATA
chinese_dict-0.2.0.dist-info/WHEEL
chinese_dict-0.2.0.dist-info/entry_points.txt
chinese_dict-0.2.0.dist-info/top_level.txt
chinese_dict-0.2.0.dist-info/RECORD
