Metadata-Version: 2.1
Name: chinese-dict
Version: 0.2.0
Summary: Mandarin dictionary
Home-page: UNKNOWN
Author: Me
Author-email: UNKNOWN
License: MIT
Platform: UNKNOWN
Requires-Dist: SQLAlchemy (==1.3.22)
Requires-Dist: treelib (==1.6.1)
